[{
  "_id": {
    "$oid": "65d706915c208e7fd4abebab"
  },
  "id": null,
  "name": "Thielen",
  "e_mail": "thielen@hs-worms.de",
  "title": "Prof. Dr.",
  "absences": [],
  "intern": true
},
{
  "_id": {
    "$oid": "65d706a45c208e7fd4abebac"
  },
  "id": null,
  "name": "Wehrstein",
  "e_mail": "Wehrstein@hs-worms.de",
  "title": "Herr",
  "absences": [],
  "intern": false
},
{
  "_id": {
    "$oid": "65d706b15c208e7fd4abebad"
  },
  "id": null,
  "name": "Schwarzer",
  "e_mail": "Schwarzer@hs-worms.de",
  "title": "Prof. Dr.",
  "absences": [],
  "intern": true
},
{
  "_id": {
    "$oid": "65d706bc5c208e7fd4abebae"
  },
  "id": null,
  "name": "Koenig",
  "e_mail": "Koenig@hs-worms.de",
  "title": "Prof. Dr.",
  "absences": [],
  "intern": true
},
{
  "_id": {
    "$oid": "65d706c75c208e7fd4abebaf"
  },
  "id": null,
  "name": "Kohler",
  "e_mail": "Kohler@hs-worms.de",
  "title": "Prof. Dr.",
  "absences": [],
  "intern": true
},
{
  "_id": {
    "$oid": "65d706d05c208e7fd4abebb0"
  },
  "id": null,
  "name": "Kessler",
  "e_mail": "Kessler@hs-worms.de",
  "title": "Prof. Dr.",
  "absences": [],
  "intern": true
},
{
  "_id": {
    "$oid": "65d706f05c208e7fd4abebb1"
  },
  "id": null,
  "name": "Heinmann",
  "e_mail": "Heinemann@hs-worms.de",
  "title": "Prof. Dr.",
  "absences": [],
  "intern": true
},
{
  "_id": {
    "$oid": "65d71ab9b21ff5d5528eba68"
  },
  "id": null,
  "name": "Werle-Rutter",
  "e_mail": "Rutter@hs-worms.de",
  "title": "Herr",
  "absences": [],
  "intern": true
},
{
  "_id": {
    "$oid": "65d71e229004f2a19971f8bc"
  },
  "id": null,
  "name": "Gloger",
  "e_mail": "Gloger@hs-worms.de",
  "title": "Prof. Dr.",
  "absences": [],
  "intern": true
},
{
  "_id": {
    "$oid": "65d73a12a421a928cd955b67"
  },
  "id": null,
  "name": "Haas",
  "e_mail": "Haas@hs-worms.de",
  "title": "Prof. Dr.",
  "absences": [],
  "intern": true
},
{
  "_id": {
    "$oid": "65d73a62a421a928cd955b69"
  },
  "id": null,
  "name": "Wendzel",
  "e_mail": "Wendzel@hs-worms.de",
  "title": "Prof. Dr.",
  "absences": [],
  "intern": true
},
{
  "_id": {
    "$oid": "65d73be5a421a928cd955b6e"
  },
  "id": null,
  "name": "Wiebel",
  "e_mail": "Wiebel@hs-worms.de",
  "title": "Prof. Dr.",
  "absences": [],
  "intern": true
}]